idepy_next/__init__.py
idepy_next/_version.py
idepy_next/errors.py
idepy_next/event.py
idepy_next/guilib.py
idepy_next/http.py
idepy_next/localization.py
idepy_next/menu.py
idepy_next/screen.py
idepy_next/util.py
idepy_next/window.py
idepy_next/__pyinstaller/__init__.py
idepy_next/__pyinstaller/hook-idepy_next.py
idepy_next/dom/__init__.py
idepy_next/dom/classlist.py
idepy_next/dom/dom.py
idepy_next/dom/element.py
idepy_next/dom/event.py
idepy_next/dom/propsdict.py
idepy_next/extra/__init__.py
idepy_next/extra/dev_utils.py
idepy_next/extra/main_export.py
idepy_next/extra/manage.py
idepy_next/extra/settings.py
idepy_next/extra/window_export.py
idepy_next/extra/env/MicrosoftEdgeWebview2Setup.exe
idepy_next/extra/env/NDP481-Web.exe
idepy_next/extra/main_utils/__init__.py
idepy_next/extra/main_utils/boot_start.py
idepy_next/extra/main_utils/builder.py
idepy_next/extra/main_utils/config.py
idepy_next/extra/main_utils/file.py
idepy_next/extra/main_utils/hotkeys.py
idepy_next/extra/main_utils/resource_pack.py
idepy_next/extra/main_utils/server.py
idepy_next/extra/main_utils/tab_manager.py
idepy_next/extra/main_utils/tray_menu.py
idepy_next/extra/main_utils/window_resizer.py
idepy_next/extra/management/__init__.py
idepy_next/extra/management/builder.py
idepy_next/extra/management/commandExecutor.py
idepy_next/extra/management/commands/__init__.py
idepy_next/extra/management/commands/build.py
idepy_next/extra/management/commands/create_base_window.py
idepy_next/extra/management/commands/init.py
idepy_next/extra/management/commands/preview.py
idepy_next/extra/templates/bootstrap_templates/base_project/elements.py
idepy_next/extra/templates/bootstrap_templates/base_project/icon.ico
idepy_next/extra/templates/bootstrap_templates/base_project/idepy.json
idepy_next/extra/templates/bootstrap_templates/base_project/main.py
idepy_next/extra/templates/bootstrap_templates/base_project/static/package.json
idepy_next-1.1.2.dist-info/LICENSE
idepy_next-1.1.2.dist-info/METADATA
idepy_next-1.1.2.dist-info/WHEEL
idepy_next-1.1.2.dist-info/entry_points.txt
idepy_next-1.1.2.dist-info/top_level.txt
idepy_next-1.1.2.dist-info/RECORD
