Metadata-Version: 2.1
Name: idepy-next
Version: 1.1.2
Summary: Build GUI for your Python program with JavaScript, HTML, and CSS, featuring Python-style data management and event binding to make development more intuitive and productive. 
Home-page: https://idepy.com
Author: IDEPY Team
Author-email: maplesunrise@foxmail.com
License: BSD3
Classifier: License :: OSI Approved :: BSD License
Classifier: Programming Language :: Python :: 3
Classifier: Programming Language :: Python :: 3.8
Classifier: Operating System :: Microsoft :: Windows :: Windows 7
Classifier: Operating System :: Microsoft :: Windows :: Windows 10
Classifier: Operating System :: Microsoft :: Windows :: Windows 11
Requires-Python: >=3.8
License-File: LICENSE
Requires-Dist: proxy-tools
Requires-Dist: typing-extensions
Requires-Dist: pythonnet
Requires-Dist: bottle
Requires-Dist: pydash
Requires-Dist: requests
Requires-Dist: jinja2
Requires-Dist: keyboard
Requires-Dist: winshell
Requires-Dist: pystray
Requires-Dist: plyer
Requires-Dist: pyinstaller
Requires-Dist: nuitka
Requires-Dist: pycryptodome
Requires-Dist: pywin32
Requires-Dist: psutil
